tilebench/__init__.py
tilebench/middleware.py
tilebench/viz.py
tilebench/resources/__init__.py
tilebench/resources/responses.py
tilebench/scripts/__init__.py
tilebench/scripts/cli.py
tilebench/static/spherical-mercator.js
tilebench/templates/index.html
tilebench-0.17.0.dist-info/METADATA
tilebench-0.17.0.dist-info/WHEEL
tilebench-0.17.0.dist-info/entry_points.txt
tilebench-0.17.0.dist-info/licenses/LICENSE
tilebench-0.17.0.dist-info/RECORD
