Metadata-Version: 2.4
Name: tilebench
Version: 0.17.0
Summary: Inspect HEAD/LIST/GET requests withing Rasterio
Project-URL: Homepage, https://github.com/developmentseed/tilebench
Project-URL: Issues, https://github.com/developmentseed/tilebench/issues
Project-URL: Source, https://github.com/developmentseed/tilebench
Author-email: Vincent Sarago <vincent@developmentseed.com>
License: MIT License
License-File: LICENSE
Classifier: Intended Audience :: Information Technology
Classifier: Intended Audience :: Science/Research
Classifier: License :: OSI Approved :: MIT License
Classifier: Programming Language :: Python :: 3
Classifier: Programming Language :: Python :: 3 :: Only
Classifier: Programming Language :: Python :: 3.11
Classifier: Programming Language :: Python :: 3.12
Classifier: Programming Language :: Python :: 3.13
Classifier: Topic :: Scientific/Engineering :: GIS
Requires-Python: >=3.11
Requires-Dist: fastapi>=0.100.0
Requires-Dist: jinja2<4.0.0,>=3.0
Requires-Dist: loguru
Requires-Dist: rasterio>=1.3.8
Requires-Dist: rio-tiler>=7.0
Requires-Dist: uvicorn[standard]
